{"cameraMode":{"drawMode":0,"name":"Shaded","section":"Shading Mode"},"sceneLighting":true,"audioPlay":false,"sceneViewState":{"m_AlwaysRefresh":false,"showFog":true,"showSkybox":true,"showFlares":true,"showImageEffects":true,"showParticleSystems":true,"showVisualEffectGraphs":true,"m_FxEnabled":true},"in2DMode":false,"pivot":{"x":-1.4000015258789063,"y":5.5,"z":-1.9000015258789063},"rotation":{"x":-0.1145525574684143,"y":-0.872256875038147,"z":0.24537181854248048,"w":-0.40723973512649538},"size":50.79705047607422,"orthographic":false}